65cc439923805ae05cc2__mypyc
pysnapify
